<?xml version="1.0" encoding="utf-8"?>
<Dependencies>
  <Source Uri="https://github.com/dotnet/dotnet" Mapping="source-build-reference-packages" Sha="cdc420f453860b662a76fcc72672ed2a65243146" BarId="288940" />
  <ToolsetDependencies>
    <Dependency Name="Microsoft.Build" Version="18.1.0-preview-25529-101">
      <Uri>https://github.com/dotnet/dotnet</Uri>
      <Sha>cdc420f453860b662a76fcc72672ed2a65243146</Sha>
    </Dependency>
    <Dependency Name="Microsoft.Build.Utilities.Core" Version="18.1.0-preview-25529-101">
      <Uri>https://github.com/dotnet/dotnet</Uri>
      <Sha>cdc420f453860b662a76fcc72672ed2a65243146</Sha>
    </Dependency>
    <Dependency Name="Microsoft.DotNet.Arcade.Sdk" Version="11.0.0-beta.25529.101">
      <Uri>https://github.com/dotnet/dotnet</Uri>
      <Sha>cdc420f453860b662a76fcc72672ed2a65243146</Sha>
    </Dependency>
    <Dependency Name="Microsoft.DotNet.GenAPI.Task" Version="10.0.100-rc.2.25529.101">
      <Uri>https://github.com/dotnet/dotnet</Uri>
      <Sha>cdc420f453860b662a76fcc72672ed2a65243146</Sha>
    </Dependency>
    <Dependency Name="Microsoft.NETCore.ILAsm" Version="10.0.0-rc.1.25529.101">
      <Uri>https://github.com/dotnet/dotnet</Uri>
      <Sha>cdc420f453860b662a76fcc72672ed2a65243146</Sha>
    </Dependency>
    <Dependency Name="Microsoft.NETCore.ILDAsm" Version="10.0.0-rc.1.25529.101">
      <Uri>https://github.com/dotnet/dotnet</Uri>
      <Sha>cdc420f453860b662a76fcc72672ed2a65243146</Sha>
    </Dependency>
  </ToolsetDependencies>
</Dependencies>
